paule/__init__.py
paule/gradient_planning.ipynb
paule/models.py
paule/paule.py
paule/util.py
paule/visualize.py
paule/vocaltractlab_api/JD3.speaker
paule/vocaltractlab_api/VocalTractLabApi.dll
paule/vocaltractlab_api/libVocalTractLabApi.dylib
paule/vocaltractlab_api/libVocalTractLabApi.so
paule-0.4.8.dist-info/LICENSE
paule-0.4.8.dist-info/METADATA
paule-0.4.8.dist-info/WHEEL
paule-0.4.8.dist-info/RECORD
