Metadata-Version: 2.3
Name: paule
Version: 0.4.8
Summary: paule implements the Predictive Articulatory speech synthesis model Utilizing Lexical Embeddings (PAULE), which is a control model for the articulatory speech synthesizer VocalTractLab (VTL).
License: GPLv3+
Author: Konstantin Sering
Author-email: konstantin.sering@uni-tuebingen.de
Requires-Python: >=3.9,<3.13
Classifier: Development Status :: 3 - Alpha
Classifier: Environment :: Console
Classifier: Intended Audience :: Science/Research
Classifier: License :: Other/Proprietary License
Classifier: Operating System :: MacOS
Classifier: Operating System :: Microsoft :: Windows
Classifier: Operating System :: POSIX :: Linux
Classifier: Programming Language :: Python :: 3
Classifier: Programming Language :: Python :: 3.9
Classifier: Programming Language :: Python :: 3.10
Classifier: Programming Language :: Python :: 3.11
Classifier: Programming Language :: Python :: 3.12
Classifier: Topic :: Scientific/Engineering
Classifier: Topic :: Scientific/Engineering :: Artificial Intelligence
Classifier: Topic :: Scientific/Engineering :: Information Analysis
Requires-Dist: librosa (>=0.9.2)
Requires-Dist: llvmlite (>=0.39.1)
Requires-Dist: matplotlib (>=3.8.0)
Requires-Dist: numba (>=0.56.4)
Requires-Dist: numpy (>=1.23.1)
Requires-Dist: pandas (>=1.4.3)
Requires-Dist: soundfile (>=0.11.0)
Requires-Dist: toml (>=0.10.2)
Requires-Dist: torch (>=1.13.1)
Requires-Dist: tqdm (>=4.64.1)
Project-URL: Homepage, https://paule.readthedocs.io/en/latest/
Project-URL: Repository, https://github.com/quantling/paule
